bacs/__init__.py
bacs/bacs.py
bacs/py.typed
bacs/version.py
bacs-0.1.11.dist-info/LICENSE
bacs-0.1.11.dist-info/METADATA
bacs-0.1.11.dist-info/WHEEL
bacs-0.1.11.dist-info/RECORD
