Metadata-Version: 2.1
Name: bacs
Version: 0.1.11
Summary: Bundle Adjustment For Camera Systems
Home-page: https://github.com/zauberzeug/bacs
License: MIT
Keywords: bundle,adjustment,cameras,points,infinity
Author: Zauberzeug GmbH
Author-email: info@zauberzeug.com
Requires-Python: >=3.8,<3.13
Classifier: License :: OSI Approved :: MIT License
Classifier: Programming Language :: Python :: 3
Classifier: Programming Language :: Python :: 3.8
Classifier: Programming Language :: Python :: 3.9
Classifier: Programming Language :: Python :: 3.10
Classifier: Programming Language :: Python :: 3.11
Classifier: Programming Language :: Python :: 3.12
Requires-Dist: numpy (>=1.21.2,<2.0.0)
Requires-Dist: scipy (>=1.10.0,<1.11.0) ; python_version == "3.8"
Requires-Dist: scipy (>=1.11.0) ; python_version >= "3.9"
Project-URL: Repository, https://github.com/zauberzeug/bacs
